<?xml version="1.0" encoding="UTF-8"?>
<objects serializationModel="Studio.02.02.00">
	<object class="AudioFile" id="{801e30d6-838b-4f1d-940a-163af59faf1a}">
		<property name="assetPath">
			<value>MUISICA 1.wav</value>
		</property>
		<property name="isStreaming">
			<value>true</value>
		</property>
		<property name="frequencyInKHz">
			<value>48</value>
		</property>
		<property name="channelCount">
			<value>2</value>
		</property>
		<property name="length">
			<value>67.636375000000001</value>
		</property>
		<relationship name="masterAssetFolder">
			<destination>{f18b0020-a1ed-4282-b50e-a0280a15628f}</destination>
		</relationship>
	</object>
</objects>
